{
  "project_info": {
    "project_number": "277484637175",
    "project_id": "tranquilmind-17e9a",
    "storage_bucket": "tranquilmind-17e9a.firebasestorage.app"
  },
  "client": [
    {
      "client_info": {
        "mobilesdk_app_id": "1:277484637175:android:4e56e70f65585033c93cf2",
        "android_client_info": {
          "package_name": "com.example.final_project"
        }
      },
      "oauth_client": [],
      "api_key": [
        {
          "current_key": "AIzaSyB3vaa29NsoLrvaFlhycTNH-D6M1dfjMEU"
        }
      ],
      "services": {
        "appinvite_service": {
          "other_platform_oauth_client": []
        }
      }
    }
  ],
  "configuration_version": "1"
}